{
  "name": "default",
  "component": "dialog",
  "createdAt": "2026-05-10T20:05:24.719Z",
  "updatedAt": "2026-05-18T15:58:43.830Z",
  "aliases": {
    "--dialog-overlay-surface": "--overlay-high",
    "--dialog-surface": "--surface-neutral-lowest",
    "--dialog-border": "--border-neutral-strong",
    "--dialog-border-width": "--border-width-2",
    "--dialog-radius": "--radius-lg",
    "--dialog-shadow": "--shadow-2xl",
    "--dialog-blur": "--blur-none",
    "--dialog-header-surface": "--surface-neutral-lower",
    "--dialog-header-border": "--border-neutral-subtle",
    "--dialog-header-border-width": "--border-width-1",
    "--dialog-header-padding": "--space-8",
    "--dialog-title": "--text-primary",
    "--dialog-title-font-family": "--font-sans",
    "--dialog-title-font-size": "--font-size-2xl",
    "--dialog-title-font-weight": "--font-weight-normal",
    "--dialog-title-line-height": "--line-height-sm",
    "--dialog-close-icon": "--text-secondary",
    "--dialog-close-icon-size": "--icon-size-xl",
    "--dialog-body-padding": "--space-16",
    "--dialog-body": "--text-secondary",
    "--dialog-body-font-family": "--font-sans",
    "--dialog-body-font-size": "--font-size-md",
    "--dialog-body-font-weight": "--font-weight-normal",
    "--dialog-body-line-height": "--line-height-md",
    "--dialog-footer-border": "--border-neutral-subtle",
    "--dialog-footer-border-width": "--border-width-1",
    "--dialog-footer-padding": "--space-16"
  }
}